referenceqvm/__init__.py
referenceqvm/api.py
referenceqvm/gates.py
referenceqvm/qam.py
referenceqvm/qvm_unitary.py
referenceqvm/qvm_wavefunction.py
referenceqvm/unitary_generator.py
referenceqvm-0.1.1.dist-info/DESCRIPTION.rst
referenceqvm-0.1.1.dist-info/METADATA
referenceqvm-0.1.1.dist-info/RECORD
referenceqvm-0.1.1.dist-info/WHEEL
referenceqvm-0.1.1.dist-info/metadata.json
referenceqvm-0.1.1.dist-info/top_level.txt
