Metadata-Version: 2.0
Name: referenceqvm
Version: 0.1.1
Summary: a reference qvm for simulation of pyQuil programs
Home-page: https://github.com/rigetticomputing/referenceqvm.git
Author: Rigetti Computing
Author-email: softapps@rigetti.com
License: LICENSE
Platform: UNKNOWN
Requires-Dist: funcsigs
Requires-Dist: numpy (>=1.11.1)
Requires-Dist: pyquil (>=1.1.1)
Requires-Dist: scipy (>=0.18.1)
